{"vehicles":[{"owner":1,"t":{"Truck":true},"speed":2.0,"capacity":100,"cargo":{"None":true},"age":2,"status":{"Driving":true},"x":298.2761315696845,"y":178.98595974687322,"destination":[2],"loc":{"Some":3}},{"owner":2,"t":{"Car":true},"speed":4.0,"capacity":25,"cargo":{"Some":{"t":{"Lumber":true},"quant":25}},"age":4,"status":{"Driving":true},"x":303.79473319220205,"y":168.61580042339386,"destination":[1],"loc":{"Some":3}},{"owner":3,"t":{"Car":true},"speed":4.0,"capacity":25,"cargo":{"Some":{"t":{"Lumber":true},"quant":25}},"age":5,"status":{"Driving":true},"x":145.60212569266332,"y":76.45406234257649,"destination":[1],"loc":{"Some":2}},{"owner":4,"t":{"Car":true},"speed":4.0,"capacity":25,"cargo":{"Some":{"t":{"Electronics":true},"quant":25}},"age":6,"status":{"Driving":true},"x":137.48314552243073,"y":270.28714137642737,"destination":[3],"loc":{"Some":5}}],"players":[{"pid":0,"ptype":{"Human":true},"money":400.0},{"pid":1,"ptype":{"AI":400},"money":57.55081777597155},{"pid":2,"ptype":{"AI":400},"money":96.78449720055036},{"pid":3,"ptype":{"AI":400},"money":97.06194090994066},{"pid":4,"ptype":{"AI":400},"money":26.438171400238858}],"gameage":7,"paused":false,"graph":{"directed":false,"type":"2D undirected graph","label":"Game Map","metadata":{"var":"str"},"nodes":[{"id":9,"lx":420.0,"ly":530.0,"accepts":[{"resource":{"Electronics":true},"stepstoinc":500,"current":21,"capacity":40,"price":4.098301208502813,"naturalprice":4.0},{"resource":{"Iron":true},"stepstoinc":500,"current":21,"capacity":40,"price":7.775815342936054,"naturalprice":7.5}],"produces":[{"resource":{"Lumber":true},"stepstoinc":40,"current":101,"capacity":200,"price":2.153933532460952,"naturalprice":2.2},{"resource":{"Produce":true},"stepstoinc":20,"current":6,"capacity":30,"price":0.717736643910272,"naturalprice":0.7}]},{"id":8,"lx":270.0,"ly":330.0,"accepts":[{"resource":{"Oil":true},"stepstoinc":500,"current":21,"capacity":40,"price":5.133774196301756,"naturalprice":5.0},{"resource":{"Iron":true},"stepstoinc":500,"current":21,"capacity":40,"price":3.4739198376836167,"naturalprice":3.5}],"produces":[{"resource":{"Lumber":true},"stepstoinc":50,"current":101,"capacity":200,"price":2.2065176290953903,"naturalprice":2.2},{"resource":{"Electronics":true},"stepstoinc":40,"current":6,"capacity":100,"price":2.882706810397361,"naturalprice":3.0}]},{"id":7,"lx":800.0,"ly":330.0,"accepts":[{"resource":{"Electronics":true},"stepstoinc":500,"current":21,"capacity":40,"price":2.9096344565297123,"naturalprice":3.0},{"resource":{"Iron":true},"stepstoinc":500,"current":21,"capacity":40,"price":4.378058688023224,"naturalprice":4.5}],"produces":[{"resource":{"Produce":true},"stepstoinc":70,"current":101,"capacity":2000,"price":1.8033810693232437,"naturalprice":1.8},{"resource":{"Oil":true},"stepstoinc":12,"current":6,"capacity":100,"price":3.1197574495155163,"naturalprice":3.0}]},{"id":6,"lx":850.0,"ly":150.0,"accepts":[{"resource":{"Produce":true},"stepstoinc":500,"current":21,"capacity":40,"price":5.999553598889247,"naturalprice":6.0},{"resource":{"Oil":true},"stepstoinc":500,"current":21,"capacity":40,"price":9.265134505045518,"naturalprice":9.5}],"produces":[{"resource":{"Iron":true},"stepstoinc":40,"current":101,"capacity":200,"price":4.129847154245564,"naturalprice":4.2},{"resource":{"Electronics":true},"stepstoinc":20,"current":40,"capacity":40,"price":0.9713009691787274,"naturalprice":1.0}]},{"id":5,"lx":120.0,"ly":280.0,"accepts":[{"resource":{"Produce":true},"stepstoinc":500,"current":21,"capacity":40,"price":8.931468405221887,"naturalprice":9.0},{"resource":{"Lumber":true},"stepstoinc":500,"current":21,"capacity":40,"price":3.4676474114154576,"naturalprice":3.5}],"produces":[{"resource":{"Oil":true},"stepstoinc":50,"current":101,"capacity":200,"price":4.162097463321812,"naturalprice":4.2},{"resource":{"Electronics":true},"stepstoinc":30,"current":176,"capacity":400,"price":4.839966622921751,"naturalprice":5.0}]},{"id":4,"lx":150.0,"ly":520.0,"accepts":[{"resource":{"Oil":true},"stepstoinc":500,"current":21,"capacity":40,"price":8.10230291328298,"naturalprice":4.0},{"resource":{"Iron":true},"stepstoinc":500,"current":21,"capacity":40,"price":6.286728797277591,"naturalprice":6.5}],"produces":[{"resource":{"Produce":true},"stepstoinc":45,"current":101,"capacity":600,"price":1.210783117749573,"naturalprice":1.2},{"resource":{"Electronics":true},"stepstoinc":40,"current":51,"capacity":100,"price":0.2921702643799947,"naturalprice":0.3}]},{"id":3,"lx":300.0,"ly":180.0,"accepts":[{"resource":{"Oil":true},"stepstoinc":500,"current":21,"capacity":40,"price":3.692406791863208,"naturalprice":3.8},{"resource":{"Electronics":true},"stepstoinc":500,"current":21,"capacity":40,"price":7.68232394490938,"naturalprice":7.5}],"produces":[{"resource":{"Produce":true},"stepstoinc":20,"current":1,"capacity":100,"price":0.19553651752477325,"naturalprice":0.2},{"resource":{"Lumber":true},"stepstoinc":25,"current":476,"capacity":1000,"price":1.9597856232460518,"naturalprice":2.0}]},{"id":2,"lx":130.0,"ly":80.0,"accepts":[{"resource":{"Electronics":true},"stepstoinc":50,"current":31,"capacity":40,"price":5.438059596469221,"naturalprice":5.6},{"resource":{"Produce":true},"stepstoinc":50,"current":21,"capacity":400,"price":4.731006649264003,"naturalprice":4.9}],"produces":[{"resource":{"Lumber":true},"stepstoinc":80,"current":76,"capacity":200,"price":2.251922363602373,"naturalprice":2.2},{"resource":{"Iron":true},"stepstoinc":90,"current":6,"capacity":100,"price":1.0898237461697193,"naturalprice":1.1}]},{"id":1,"lx":350.0,"ly":30.0,"accepts":[{"resource":{"Lumber":true},"stepstoinc":100,"current":21,"capacity":40,"price":5.193220681585399,"naturalprice":5.0},{"resource":{"Iron":true},"stepstoinc":50,"current":21,"capacity":80,"price":7.7885471982702095,"naturalprice":7.5}],"produces":[{"resource":{"Oil":true},"stepstoinc":100,"current":101,"capacity":200,"price":1.1747570900797888,"naturalprice":1.2},{"resource":{"Electronics":true},"stepstoinc":85,"current":6,"capacity":100,"price":1.0244246905966006,"naturalprice":1.0}]},{"id":0,"lx":510.0,"ly":320.0,"accepts":[{"resource":{"Oil":true},"stepstoinc":50,"current":21,"capacity":40,"price":4.8872914618062175,"naturalprice":5.0},{"resource":{"Iron":true},"stepstoinc":50,"current":21,"capacity":40,"price":3.536085581676929,"naturalprice":3.5}],"produces":[{"resource":{"Lumber":true},"stepstoinc":90,"current":101,"capacity":200,"price":2.176516401065855,"naturalprice":2.2},{"resource":{"Electronics":true},"stepstoinc":50,"current":6,"capacity":100,"price":2.9165144979185973,"naturalprice":3.0}]}],"edges":[{"owner":-1,"lstart":9,"lend":0,"age":0,"speed":3.0,"length":269.3},{"owner":-1,"lstart":5,"lend":8,"age":0,"speed":3.0,"length":158.1},{"owner":2,"lstart":6,"lend":7,"age":0,"speed":3.0,"length":186.8},{"owner":-1,"lstart":0,"lend":7,"age":0,"speed":3.0,"length":292.7},{"owner":4,"lstart":5,"lend":3,"age":0,"speed":0.0,"length":180.0},{"owner":1,"lstart":2,"lend":3,"age":0,"speed":0.0,"length":170.0},{"owner":2,"lstart":3,"lend":1,"age":0,"speed":0.0,"length":50.0},{"owner":3,"lstart":2,"lend":1,"age":0,"speed":3.0,"length":225.6},{"owner":-1,"lstart":1,"lend":0,"age":0,"speed":3.0,"length":305.3}]}}